{
    "data": [
        {
            "symbol": "X1-RZ49",
            "sectorSymbol": "X1",
            "type": "BLUE_STAR",
            "x": 209,
            "y": -280,
            "waypoints": [
                {
                    "symbol": "X1-RZ49-41010E",
                    "type": "ASTEROID_FIELD",
                    "x": -6,
                    "y": 20
                }
            ],
            "factions": []
        },
        {
            "symbol": "X1-DC65",
            "sectorSymbol": "X1",
            "type": "ORANGE_STAR",
            "x": -50,
            "y": -321,
            "waypoints": [
                {
                    "symbol": "X1-DC65-31400C",
                    "type": "PLANET",
                    "x": 25,
                    "y": -28
                },
                {
                    "symbol": "X1-DC65-70571A",
                    "type": "MOON",
                    "x": 25,
                    "y": -28
                }
            ],
            "factions": []
        },
        {
            "symbol": "X1-NA61",
            "sectorSymbol": "X1",
            "type": "ORANGE_STAR",
            "x": 380,
            "y": 86,
            "waypoints": [
                {
                    "symbol": "X1-NA61-83010Z",
                    "type": "PLANET",
                    "x": 39,
                    "y": 24
                },
                {
                    "symbol": "X1-NA61-13571D",
                    "type": "PLANET",
                    "x": 4,
                    "y": -51
                },
                {
                    "symbol": "X1-NA61-82842F",
                    "type": "MOON",
                    "x": 4,
                    "y": -51
                },
                {
                    "symbol": "X1-NA61-07543E",
                    "type": "MOON",
                    "x": 4,
                    "y": -51
                }
            ],
            "factions": []
        },
        {
            "symbol": "X1-QT96",
            "sectorSymbol": "X1",
            "type": "YOUNG_STAR",
            "x": -243,
            "y": -205,
            "waypoints": [
                {
                    "symbol": "X1-QT96-20100E",
                    "type": "PLANET",
                    "x": -9,
                    "y": 19
                },
                {
                    "symbol": "X1-QT96-89021X",
                    "type": "PLANET",
                    "x": -44,
                    "y": 20
                },
                {
                    "symbol": "X1-QT96-80472B",
                    "type": "PLANET",
                    "x": -8,
                    "y": -72
                },
                {
                    "symbol": "X1-QT96-71623Z",
                    "type": "MOON",
                    "x": -8,
                    "y": -72
                },
                {
                    "symbol": "X1-QT96-73294C",
                    "type": "JUMP_GATE",
                    "x": -5,
                    "y": -77
                }
            ],
            "factions": [
                {
                    "symbol": "COSMIC"
                }
            ]
        },
        {
            "symbol": "X1-QG6",
            "sectorSymbol": "X1",
            "type": "RED_STAR",
            "x": -262,
            "y": 229,
            "waypoints": [
                {
                    "symbol": "X1-QG6-28130E",
                    "type": "PLANET",
                    "x": 24,
                    "y": -10
                },
                {
                    "symbol": "X1-QG6-95471D",
                    "type": "PLANET",
                    "x": -5,
                    "y": -47
                },
                {
                    "symbol": "X1-QG6-08312X",
                    "type": "MOON",
                    "x": -5,
                    "y": -47
                }
            ],
            "factions": []
        },
        {
            "symbol": "X1-UG95",
            "sectorSymbol": "X1",
            "type": "BLUE_STAR",
            "x": -13,
            "y": -335,
            "waypoints": [
                {
                    "symbol": "X1-UG95-58970C",
                    "type": "PLANET",
                    "x": 28,
                    "y": 30
                }
            ],
            "factions": []
        },
        {
            "symbol": "X1-CS97",
            "sectorSymbol": "X1",
            "type": "BLUE_STAR",
            "x": -332,
            "y": 50,
            "waypoints": [
                {
                    "symbol": "X1-CS97-40260F",
                    "type": "PLANET",
                    "x": 29,
                    "y": -30
                },
                {
                    "symbol": "X1-CS97-61141Z",
                    "type": "MOON",
                    "x": 29,
                    "y": -30
                },
                {
                    "symbol": "X1-CS97-03422B",
                    "type": "MOON",
                    "x": 29,
                    "y": -30
                },
                {
                    "symbol": "X1-CS97-23403B",
                    "type": "JUMP_GATE",
                    "x": -47,
                    "y": -10
                }
            ],
            "factions": [
                {
                    "symbol": "COSMIC"
                }
            ]
        },
        {
            "symbol": "X1-KJ81",
            "sectorSymbol": "X1",
            "type": "YOUNG_STAR",
            "x": -327,
            "y": -44,
            "waypoints": [],
            "factions": []
        },
        {
            "symbol": "X1-TR93",
            "sectorSymbol": "X1",
            "type": "UNSTABLE",
            "x": 63,
            "y": -339,
            "waypoints": [],
            "factions": []
        },
        {
            "symbol": "X1-FP13",
            "sectorSymbol": "X1",
            "type": "ORANGE_STAR",
            "x": 326,
            "y": 240,
            "waypoints": [
                {
                    "symbol": "X1-FP13-92460B",
                    "type": "PLANET",
                    "x": -38,
                    "y": 10
                },
                {
                    "symbol": "X1-FP13-76021Z",
                    "type": "MOON",
                    "x": -38,
                    "y": 10
                },
                {
                    "symbol": "X1-FP13-31472Z",
                    "type": "MOON",
                    "x": -38,
                    "y": 10
                },
                {
                    "symbol": "X1-FP13-54603E",
                    "type": "PLANET",
                    "x": -51,
                    "y": 38
                },
                {
                    "symbol": "X1-FP13-40384E",
                    "type": "MOON",
                    "x": -51,
                    "y": 38
                },
                {
                    "symbol": "X1-FP13-11685B",
                    "type": "MOON",
                    "x": -51,
                    "y": 38
                }
            ],
            "factions": []
        },
        {
            "symbol": "X1-QZ84",
            "sectorSymbol": "X1",
            "type": "ORANGE_STAR",
            "x": 325,
            "y": -195,
            "waypoints": [
                {
                    "symbol": "X1-QZ84-64030C",
                    "type": "PLANET",
                    "x": -20,
                    "y": 18
                },
                {
                    "symbol": "X1-QZ84-58011X",
                    "type": "MOON",
                    "x": -20,
                    "y": 18
                },
                {
                    "symbol": "X1-QZ84-85792C",
                    "type": "MOON",
                    "x": -20,
                    "y": 18
                },
                {
                    "symbol": "X1-QZ84-48723E",
                    "type": "PLANET",
                    "x": 26,
                    "y": 35
                },
                {
                    "symbol": "X1-QZ84-16824X",
                    "type": "MOON",
                    "x": 26,
                    "y": 35
                },
                {
                    "symbol": "X1-QZ84-51575F",
                    "type": "PLANET",
                    "x": -18,
                    "y": 70
                },
                {
                    "symbol": "X1-QZ84-06746B",
                    "type": "MOON",
                    "x": -18,
                    "y": 70
                },
                {
                    "symbol": "X1-QZ84-53277F",
                    "type": "MOON",
                    "x": -18,
                    "y": 70
                },
                {
                    "symbol": "X1-QZ84-50108D",
                    "type": "ASTEROID_FIELD",
                    "x": 31,
                    "y": 89
                }
            ],
            "factions": []
        },
        {
            "symbol": "X1-PB90",
            "sectorSymbol": "X1",
            "type": "BLUE_STAR",
            "x": 149,
            "y": -325,
            "waypoints": [
                {
                    "symbol": "X1-PB90-38480F",
                    "type": "PLANET",
                    "x": 10,
                    "y": 35
                },
                {
                    "symbol": "X1-PB90-18551E",
                    "type": "MOON",
                    "x": 10,
                    "y": 35
                },
                {
                    "symbol": "X1-PB90-32782F",
                    "type": "MOON",
                    "x": 10,
                    "y": 35
                }
            ],
            "factions": []
        },
        {
            "symbol": "X1-X39",
            "sectorSymbol": "X1",
            "type": "ORANGE_STAR",
            "x": -3,
            "y": -344,
            "waypoints": [
                {
                    "symbol": "X1-X39-77190D",
                    "type": "PLANET",
                    "x": -16,
                    "y": 15
                },
                {
                    "symbol": "X1-X39-30741F",
                    "type": "PLANET",
                    "x": 38,
                    "y": 12
                },
                {
                    "symbol": "X1-X39-08422Z",
                    "type": "MOON",
                    "x": 38,
                    "y": 12
                },
                {
                    "symbol": "X1-X39-18213X",
                    "type": "GAS_GIANT",
                    "x": 37,
                    "y": 32
                },
                {
                    "symbol": "X1-X39-10784F",
                    "type": "ASTEROID_FIELD",
                    "x": 46,
                    "y": 38
                }
            ],
            "factions": []
        },
        {
            "symbol": "X1-SD17",
            "sectorSymbol": "X1",
            "type": "RED_STAR",
            "x": 339,
            "y": 229,
            "waypoints": [
                {
                    "symbol": "X1-SD17-34130F",
                    "type": "PLANET",
                    "x": 31,
                    "y": 19
                },
                {
                    "symbol": "X1-SD17-45881E",
                    "type": "MOON",
                    "x": 31,
                    "y": 19
                },
                {
                    "symbol": "X1-SD17-02092E",
                    "type": "GAS_GIANT",
                    "x": 42,
                    "y": 18
                }
            ],
            "factions": []
        },
        {
            "symbol": "X1-XK30",
            "sectorSymbol": "X1",
            "type": "ORANGE_STAR",
            "x": 390,
            "y": -70,
            "waypoints": [
                {
                    "symbol": "X1-XK30-65030C",
                    "type": "PLANET",
                    "x": -26,
                    "y": 26
                },
                {
                    "symbol": "X1-XK30-97191E",
                    "type": "MOON",
                    "x": -26,
                    "y": 26
                },
                {
                    "symbol": "X1-XK30-42422D",
                    "type": "PLANET",
                    "x": -31,
                    "y": 43
                },
                {
                    "symbol": "X1-XK30-26393D",
                    "type": "MOON",
                    "x": -31,
                    "y": 43
                },
                {
                    "symbol": "X1-XK30-82484B",
                    "type": "GAS_GIANT",
                    "x": 74,
                    "y": 1
                },
                {
                    "symbol": "X1-XK30-76195A",
                    "type": "ASTEROID_FIELD",
                    "x": -42,
                    "y": -82
                }
            ],
            "factions": []
        },
        {
            "symbol": "X1-XN15",
            "sectorSymbol": "X1",
            "type": "RED_STAR",
            "x": -294,
            "y": -160,
            "waypoints": [
                {
                    "symbol": "X1-XN15-24140C",
                    "type": "PLANET",
                    "x": 8,
                    "y": 26
                },
                {
                    "symbol": "X1-XN15-44571X",
                    "type": "MOON",
                    "x": 8,
                    "y": 26
                },
                {
                    "symbol": "X1-XN15-06482Z",
                    "type": "PLANET",
                    "x": -38,
                    "y": 42
                },
                {
                    "symbol": "X1-XN15-38423C",
                    "type": "MOON",
                    "x": -38,
                    "y": 42
                },
                {
                    "symbol": "X1-XN15-33274X",
                    "type": "PLANET",
                    "x": 70,
                    "y": 20
                },
                {
                    "symbol": "X1-XN15-38905B",
                    "type": "MOON",
                    "x": 70,
                    "y": 20
                },
                {
                    "symbol": "X1-XN15-68316E",
                    "type": "GAS_GIANT",
                    "x": 80,
                    "y": 62
                },
                {
                    "symbol": "X1-XN15-15837X",
                    "type": "JUMP_GATE",
                    "x": -10,
                    "y": 131
                }
            ],
            "factions": [
                {
                    "symbol": "COSMIC"
                }
            ]
        },
        {
            "symbol": "X1-QV97",
            "sectorSymbol": "X1",
            "type": "ORANGE_STAR",
            "x": 401,
            "y": -25,
            "waypoints": [
                {
                    "symbol": "X1-QV97-44010F",
                    "type": "PLANET",
                    "x": -11,
                    "y": 39
                },
                {
                    "symbol": "X1-QV97-25781B",
                    "type": "MOON",
                    "x": -11,
                    "y": 39
                },
                {
                    "symbol": "X1-QV97-63362A",
                    "type": "PLANET",
                    "x": 6,
                    "y": -64
                },
                {
                    "symbol": "X1-QV97-98283X",
                    "type": "MOON",
                    "x": 6,
                    "y": -64
                },
                {
                    "symbol": "X1-QV97-57014F",
                    "type": "GAS_GIANT",
                    "x": 42,
                    "y": 58
                }
            ],
            "factions": []
        },
        {
            "symbol": "X1-RG76",
            "sectorSymbol": "X1",
            "type": "YOUNG_STAR",
            "x": -223,
            "y": -253,
            "waypoints": [
                {
                    "symbol": "X1-RG76-56470X",
                    "type": "PLANET",
                    "x": 19,
                    "y": -16
                },
                {
                    "symbol": "X1-RG76-27871X",
                    "type": "GAS_GIANT",
                    "x": 8,
                    "y": 44
                },
                {
                    "symbol": "X1-RG76-07632D",
                    "type": "GAS_GIANT",
                    "x": -29,
                    "y": 43
                }
            ],
            "factions": []
        },
        {
            "symbol": "X1-XV63",
            "sectorSymbol": "X1",
            "type": "YOUNG_STAR",
            "x": -220,
            "y": -258,
            "waypoints": [
                {
                    "symbol": "X1-XV63-31250C",
                    "type": "PLANET",
                    "x": -42,
                    "y": 12
                },
                {
                    "symbol": "X1-XV63-31251Z",
                    "type": "MOON",
                    "x": -42,
                    "y": 12
                },
                {
                    "symbol": "X1-XV63-74712X",
                    "type": "MOON",
                    "x": -42,
                    "y": 12
                },
                {
                    "symbol": "X1-XV63-80843C",
                    "type": "MOON",
                    "x": -42,
                    "y": 12
                },
                {
                    "symbol": "X1-XV63-52794A",
                    "type": "PLANET",
                    "x": 21,
                    "y": -68
                },
                {
                    "symbol": "X1-XV63-00015B",
                    "type": "MOON",
                    "x": 21,
                    "y": -68
                },
                {
                    "symbol": "X1-XV63-61626Z",
                    "type": "GAS_GIANT",
                    "x": -91,
                    "y": 15
                }
            ],
            "factions": []
        },
        {
            "symbol": "X1-HN33",
            "sectorSymbol": "X1",
            "type": "BLUE_STAR",
            "x": -246,
            "y": 280,
            "waypoints": [
                {
                    "symbol": "X1-HN33-31680A",
                    "type": "PLANET",
                    "x": 7,
                    "y": -26
                },
                {
                    "symbol": "X1-HN33-95781X",
                    "type": "MOON",
                    "x": 7,
                    "y": -26
                },
                {
                    "symbol": "X1-HN33-04992D",
                    "type": "PLANET",
                    "x": -32,
                    "y": 17
                },
                {
                    "symbol": "X1-HN33-03463B",
                    "type": "MOON",
                    "x": -32,
                    "y": 17
                },
                {
                    "symbol": "X1-HN33-54704D",
                    "type": "MOON",
                    "x": -32,
                    "y": 17
                },
                {
                    "symbol": "X1-HN33-58015D",
                    "type": "GAS_GIANT",
                    "x": 46,
                    "y": 32
                },
                {
                    "symbol": "X1-HN33-88566B",
                    "type": "ASTEROID_FIELD",
                    "x": -75,
                    "y": -32
                }
            ],
            "factions": []
        }
    ],
    "meta": {
        "total": 7000,
        "page": 14,
        "limit": 20
    }
}